versus.py
versus-0.1.4.dist-info/licenses/LICENSE
versus-0.1.4.dist-info/METADATA
versus-0.1.4.dist-info/WHEEL
versus-0.1.4.dist-info/top_level.txt
versus-0.1.4.dist-info/RECORD
